radicale_dovecot_auth/__about__.py
radicale_dovecot_auth/__init__.py
radicale_dovecot_auth/dovecot_auth.py
radicale_dovecot_auth-0.4.1.dist-info/COPYING
radicale_dovecot_auth-0.4.1.dist-info/METADATA
radicale_dovecot_auth-0.4.1.dist-info/WHEEL
radicale_dovecot_auth-0.4.1.dist-info/top_level.txt
radicale_dovecot_auth-0.4.1.dist-info/RECORD
