Metadata-Version: 2.1
Name: radicale-dovecot-auth
Version: 0.4.1
Summary: Dovecot authentication plugin for Radicale
Home-page: https://github.com/Arvedui/radicale-dovecot-auth
Author: Arvedui
Author-email: asseon@posteo.de
License: GNU GPL v3
Platform: UNKNOWN
Classifier: Development Status :: 5 - Production/Stable
Classifier: Operating System :: POSIX
Classifier: License :: OSI Approved :: GNU General Public License v2 (GPLv2)
Classifier: Programming Language :: Python :: 3
Classifier: Programming Language :: Python :: 3.3
Classifier: Programming Language :: Python :: 3.4
Classifier: Programming Language :: Python :: 3.5
Classifier: Programming Language :: Python :: 3.6
Classifier: Programming Language :: Python :: 3.7
Classifier: Programming Language :: Python :: 3.8
Requires-Dist: radicale
